[
    {
        "id": "73c1c7e8-55c6-4089-981a-23b76df8512d",
        "name": "Borda Quebrada",
        "image_file_id": "locations/2026/891dee80-b60a-49fd-9df9-39e728217de8-197.png",
        "image_url": null,
        "initiative_elements": "[\"air\"]",
        "abilities": "[{\"effectType\": \"increase\", \"targetScope\": \"all_creatures\", \"targetTribes\": [], \"stats\": [\"speed\"], \"value\": 5, \"cardTypes\": [\"creature\"], \"battleRules\": {\"type\": \"stat_modifier\", \"requiresTarget\": true, \"usageLimitPerTurn\": null, \"notes\": \"Aumenta velocidade das criaturas em 5.\", \"payload\": null}, \"description\": \"Aumenta a velocidade das criaturas em 5\"}, {\"effectType\": \"decrease\", \"targetScope\": \"all_creatures\", \"targetTribes\": [], \"stats\": [\"wisdom\"], \"value\": 5, \"cardTypes\": [\"attack\"], \"battleRules\": {\"type\": \"stat_modifier\", \"requiresTarget\": false, \"usageLimitPerTurn\": null, \"notes\": \"Reduz dano de ataques de Sabedoria em 5.\", \"payload\": {\"appliesTo\": \"attack_damage\", \"attackStat\": \"wisdom\"}}, \"description\": \"O dano causado por ataques de sabedoria é reduzido em 5\"}]",
        "created_at": "2026-02-14 16:30:57.472189+00",
        "updated_at": "2026-02-14 16:30:57.472189+00",
        "tribes": "[]",
        "rarity": "comum"
    },
    {
        "id": "f4a7b2e1-9c3d-4e5f-a6b7-8c9d0e1f2a3b",
        "name": "Toca dos Lutadores",
        "image_file_id": "",
        "image_url": null,
        "initiative_elements": "[\"speed\"]",
        "abilities": "[{\"effectType\": \"special\", \"targetScope\": \"none\", \"targetTribes\": [], \"stats\": [\"none\"], \"value\": 0, \"cardTypes\": [\"attack\"], \"battleRules\": {\"type\": \"shuffle_attack_discard_into_deck\", \"requiresTarget\": false, \"usageLimitPerTurn\": 1, \"notes\": \"Embaralha descarte de ataques no baralho de ataques.\", \"payload\": null}, \"description\": \"Quando este se torna o Local ativo, cada jogador embaralha sua pilha de descarte de ataques e seu Baralho de Ataques juntos\"}, {\"effectType\": \"increase\", \"targetScope\": \"all_creatures\", \"targetTribes\": [], \"stats\": [\"all\"], \"value\": 5, \"cardTypes\": [\"creature\"], \"battleRules\": {\"type\": \"stat_modifier\", \"requiresTarget\": true, \"usageLimitPerTurn\": null, \"notes\": \"Superar todas as disciplinas +5.\", \"payload\": {\"keyword\": \"outperform\"}}, \"description\": \"Todas as Criaturas ganham Superar todas as Disciplinas 5\"}]",
        "created_at": "2026-02-15 11:16:57+00",
        "updated_at": "2026-02-15 11:16:57+00",
        "tribes": "[]",
        "rarity": "incomum"
    },
    {
        "id": "d5e6f7a8-1b2c-3d4e-5f6g-7h8i9j0k1l2m",
        "name": "Arsenal de Bodal",
        "image_file_id": "",
        "image_url": null,
        "initiative_elements": "[\"wisdom\"]",
        "abilities": "[{\"effectType\": \"special\", \"targetScope\": \"none\", \"targetTribes\": [], \"stats\": [\"none\"], \"value\": 0, \"cardTypes\": [\"equipment\", \"creature\"], \"battleRules\": {\"type\": \"return_battlegear_from_discard\", \"requiresTarget\": false, \"usageLimitPerTurn\": 1, \"notes\": \"Retorna battlegear da pilha e equipa criatura não equipada.\", \"payload\": null}, \"description\": \"Quando este se torna o Local ativo, cada jogador pode retornar um Battlegear de sua pilha de descarte para o jogo e equipá-lo em uma Criatura não equipada que aquele jogador controla\"}]",
        "created_at": "2026-02-15 11:16:57+00",
        "updated_at": "2026-02-15 11:16:57+00",
        "tribes": "[]",
        "rarity": "ultra raro"
    },
    {
        "id": "e2a1b3c4-d5e6-4f7g-8h9i-j0k1l2m3n4o5",
        "name": "Cabana de Gambreor",
        "image_file_id": null,
        "image_url": null,
        "initiative_elements": "[\"power\"]",
        "abilities": "[{\"effectType\": \"gain\", \"targetScope\": \"own_creatures\", \"targetTribes\": [], \"stats\": [\"none\"], \"value\": 5, \"cardTypes\": [\"creature\"], \"battleRules\": {\"type\": \"stat_modifier\", \"requiresTarget\": true, \"usageLimitPerTurn\": null, \"notes\": \"Concede À Prova de Fogo 5 para suas criaturas.\", \"payload\": {\"keyword\": \"fireproof\", \"amount\": 5}}, \"description\": \"Criaturas que você controla ganham À Prova de Fogo 5\"}, {\"effectType\": \"decrease\", \"targetScope\": \"all_creatures\", \"targetTribes\": [], \"stats\": [\"all\"], \"value\": 10, \"cardTypes\": [\"mugic\", \"ability\"], \"battleRules\": {\"type\": \"stat_modifier\", \"requiresTarget\": false, \"usageLimitPerTurn\": null, \"notes\": \"Reduções por Mugic/habilidade são reduzidas em 10.\", \"payload\": {\"appliesTo\": \"discipline_reduction\"}}, \"description\": \"Se um Mugic ou habilidade reduziria a Disciplina de uma Criatura, aquele Mugic ou habilidade reduz a Disciplina em 10 a menos\"}, {\"effectType\": \"special\", \"targetScope\": \"none\", \"targetTribes\": [], \"stats\": [\"none\"], \"value\": 0, \"cardTypes\": [\"location\"], \"battleRules\": {\"type\": \"generic_special\", \"requiresTarget\": false, \"usageLimitPerTurn\": null, \"notes\": \"Único\", \"payload\": {\"unique\": true}}, \"description\": \"Único\"}]",
        "created_at": "2026-02-15 11:25:00+00",
        "updated_at": "2026-02-15 11:25:00+00",
        "tribes": "[]",
        "rarity": "super raro"
    },
    {
        "id": "a1b2c3d4-e5f6-4a7b-8c9d-0e1f2g3h4i5j",
        "name": "Câmara das Ondas",
        "image_file_id": null,
        "image_url": null,
        "initiative_elements": "[\"wisdom\"]",
        "abilities": "[{\"effectType\": \"decrease\", \"targetScope\": \"all_creatures\", \"targetTribes\": [], \"stats\": [\"all\"], \"value\": 10, \"cardTypes\": [\"creature\"], \"battleRules\": {\"type\": \"stat_modifier\", \"requiresTarget\": true, \"usageLimitPerTurn\": null, \"notes\": \"Reduz 10 em todas as disciplinas.\", \"payload\": null}, \"description\": \"Criaturas perdem 10 em todas as Disciplinas\"}]",
        "created_at": "2026-02-15 11:25:00+00",
        "updated_at": "2026-02-15 11:25:00+00",
        "tribes": "[]",
        "rarity": "comum"
    },
    {
        "id": "b2c3d4e5-f6g7-4h8i-9j0k-1l2m3n4o5p6q",
        "name": "Gongo de Alcance Mortal",
        "image_file_id": null,
        "image_url": null,
        "initiative_elements": "[\"fire\"]",
        "abilities": "[{\"effectType\": \"increase\", \"targetScope\": \"all_creatures\", \"targetTribes\": [], \"stats\": [\"all\"], \"value\": 15, \"cardTypes\": [\"creature\"], \"battleRules\": {\"type\": \"stat_modifier\", \"requiresTarget\": true, \"usageLimitPerTurn\": null, \"notes\": \"Chefes recebem +15 em todas disciplinas.\", \"payload\": {\"condition\": \"is_chieftain\"}}, \"description\": \"Chefes ganham 15 em todas as Disciplinas\"}, {\"effectType\": \"gain\", \"targetScope\": \"all_creatures\", \"targetTribes\": [], \"stats\": [\"none\"], \"value\": 5, \"cardTypes\": [\"creature\"], \"battleRules\": {\"type\": \"stat_modifier\", \"requiresTarget\": true, \"usageLimitPerTurn\": null, \"notes\": \"Chefes ganham Água 5.\", \"payload\": {\"condition\": \"is_chieftain\", \"keyword\": \"water\", \"amount\": 5}}, \"description\": \"Chefes ganham Água 5\"}]",
        "created_at": "2026-02-15 11:25:00+00",
        "updated_at": "2026-02-15 11:25:00+00",
        "tribes": "[]",
        "rarity": "super raro"
    },
    {
        "id": "76e3a1b4-2c9d-4e5f-b6a7-8c9d0e1f2a3c",
        "name": "Galeria da Colmeia",
        "image_file_id": null,
        "image_url": null,
        "initiative_elements": "[\"earth\"]",
        "abilities": "[{\"effectType\": \"increase\", \"targetScope\": \"engaged_creatures\", \"targetTribes\": [], \"stats\": [\"courage\"], \"value\": 5, \"cardTypes\": [\"creature\"], \"battleRules\": {\"type\": \"stat_modifier\", \"requiresTarget\": true, \"usageLimitPerTurn\": null, \"notes\": \"Criaturas engajadas ganham Superar Coragem 5.\", \"payload\": {\"keyword\": \"outperform\"}}, \"description\": \"Criaturas Engajadas ganham Superar Coragem 5\"}, {\"effectType\": \"decrease\", \"targetScope\": \"all_creatures\", \"targetTribes\": [], \"stats\": [\"power\"], \"value\": 5, \"cardTypes\": [\"attack\"], \"battleRules\": {\"type\": \"stat_modifier\", \"requiresTarget\": false, \"usageLimitPerTurn\": null, \"notes\": \"Reduz dano de ataques de Poder em 5.\", \"payload\": {\"appliesTo\": \"attack_damage\", \"attackStat\": \"power\"}}, \"description\": \"Dano causado por ataques de Poder é reduzido em 5\"}]",
        "created_at": "2026-02-15 11:30:00+00",
        "updated_at": "2026-02-15 11:30:00+00",
        "tribes": "[]",
        "rarity": "comum"
    },
    {
        "id": "87f4b2c5-3d0e-4f6g-a7b8-9c0d1e2f3a4b",
        "name": "Noite no Pântano Sombrio",
        "image_file_id": null,
        "image_url": null,
        "initiative_elements": "[\"mipedian\"]",
        "abilities": "[{\"effectType\": \"negate\", \"targetScope\": \"all_creatures\", \"targetTribes\": [], \"stats\": [\"none\"], \"value\": 0, \"cardTypes\": [\"mugic\", \"ability\"], \"battleRules\": {\"type\": \"cannot_relocate_creatures\", \"requiresTarget\": false, \"usageLimitPerTurn\": null, \"notes\": \"Mugic/habilidades de realocação não têm efeito.\", \"payload\": null}, \"description\": \"Mugic e habilidades que realocam uma Criatura não têm efeito\"}]",
        "created_at": "2026-02-15 11:30:00+00",
        "updated_at": "2026-02-15 11:30:00+00",
        "tribes": "[]",
        "rarity": "incomum"
    },
    {
        "id": "98g5c3d6-4e1f-5g7h-b8c9-0d1e2f3a4b5c",
        "name": "Salão da Fadiga",
        "image_file_id": null,
        "image_url": null,
        "initiative_elements": "[\"speed\"]",
        "abilities": "[{\"effectType\": \"decrease\", \"targetScope\": \"engaged_creatures\", \"targetTribes\": [], \"stats\": [\"power\", \"speed\"], \"value\": 5, \"cardTypes\": [\"creature\"], \"battleRules\": {\"type\": \"stat_modifier\", \"requiresTarget\": true, \"usageLimitPerTurn\": null, \"notes\": \"Criaturas engajadas recebem Exaustão Poder e Velocidade 5.\", \"payload\": {\"keyword\": \"exhaust\"}}, \"description\": \"Criaturas Engajadas ganham Exaustão Poder 5 e Exaustão Velocidade 5\"}]",
        "created_at": "2026-02-15 11:30:00+00",
        "updated_at": "2026-02-15 11:30:00+00",
        "tribes": "[]",
        "rarity": "incomum"
    },
    {
        "id": "09h6d4e7-5f2g-6h8i-c9d0-1e2f3a4b5c6d",
        "name": "O Coração da Selva",
        "image_file_id": null,
        "image_url": null,
        "initiative_elements": "[\"overworld\"]",
        "abilities": "[{\"effectType\": \"special\", \"targetScope\": \"engaged_creatures\", \"targetTribes\": [], \"stats\": [\"none\"], \"value\": 0, \"cardTypes\": [\"mugic\", \"ability\"], \"battleRules\": {\"type\": \"shared_engaged_effect\", \"requiresTarget\": false, \"usageLimitPerTurn\": null, \"notes\": \"Alterações de disciplina em uma criatura engajada afetam as duas.\", \"payload\": null}, \"description\": \"Mugic e habilidades que alteram as Disciplinas de uma criatura engajada afetam ambas as Criaturas engajadas\"}, {\"effectType\": \"increase\", \"targetScope\": \"all_creatures\", \"targetTribes\": [], \"stats\": [\"all\"], \"value\": 10, \"cardTypes\": [\"creature\"], \"battleRules\": {\"type\": \"stat_modifier\", \"requiresTarget\": true, \"usageLimitPerTurn\": null, \"notes\": \"Miragem: criaturas neste espaço ganham +10 em todas disciplinas.\", \"payload\": {\"mirage\": true}}, \"description\": \"Miragem: Criaturas neste espaço ganham 10 em todas as Disciplinas\"}, {\"effectType\": \"special\", \"targetScope\": \"none\", \"targetTribes\": [], \"stats\": [\"none\"], \"value\": 0, \"cardTypes\": [\"location\"], \"battleRules\": {\"type\": \"generic_special\", \"requiresTarget\": false, \"usageLimitPerTurn\": null, \"notes\": \"Único\", \"payload\": {\"unique\": true}}, \"description\": \"Único\"}]",
        "created_at": "2026-02-15 11:30:00+00",
        "updated_at": "2026-02-15 11:30:00+00",
        "tribes": "[]",
        "rarity": "super raro"
    },
    {
        "id": "a2b3c4d5-e6f7-4g8h-9i0j-k1l2m3n4o5p6",
        "name": "O Infectório",
        "image_file_id": null,
        "image_url": null,
        "initiative_elements": "[\"courage\"]",
        "abilities": "[{\"effectType\": \"damage\", \"targetScope\": \"engaged_creatures\", \"targetTribes\": [], \"stats\": [\"energy\"], \"value\": 15, \"cardTypes\": [\"creature\"], \"battleRules\": {\"type\": \"damage_on_activation\", \"requiresTarget\": true, \"usageLimitPerTurn\": 1, \"notes\": \"Aplica em criaturas engajadas infectadas que não sejam Danian.\", \"payload\": {\"trigger\": \"on_combat_start\", \"excludeTribe\": \"danian\", \"requiresInfected\": true}}, \"description\": \"No início do combate, cause 15 de dano a Criaturas não-Danian engajadas e infectadas\"}]",
        "created_at": "2026-02-15 11:35:00+00",
        "updated_at": "2026-02-15 11:35:00+00",
        "tribes": "[\"danian\"]",
        "rarity": "comum"
    },
    {
        "id": "b3c4d5e6-f7g8-4h9i-0j1k-l2m3n4o5p6q7",
        "name": "Posto Avançado Ijahni",
        "image_file_id": null,
        "image_url": null,
        "initiative_elements": "[\"air\"]",
        "abilities": "[{\"effectType\": \"decrease\", \"targetScope\": \"own_creatures\", \"targetTribes\": [], \"stats\": [\"energy\"], \"value\": 10, \"cardTypes\": [\"creature\"], \"battleRules\": {\"type\": \"stat_modifier\", \"requiresTarget\": true, \"usageLimitPerTurn\": null, \"notes\": \"Suas criaturas perdem 10 de energia.\", \"payload\": null}, \"description\": \"Suas Criaturas perdem 10 de Energia\"}, {\"effectType\": \"special\", \"targetScope\": \"all_creatures\", \"targetTribes\": [], \"stats\": [\"none\"], \"value\": 0, \"cardTypes\": [\"creature\"], \"battleRules\": {\"type\": \"movement_lock_unless_pay_mugic\", \"requiresTarget\": true, \"usageLimitPerTurn\": null, \"notes\": \"Miragem de travamento de movimento com custo de 1 Mugic.\", \"payload\": {\"mugicCost\": 1}}, \"description\": \"Miragem: Criaturas não podem se mover para fora deste espaço a menos que seu controlador pague 1 Mugic de qualquer Criatura que controla\"}]",
        "created_at": "2026-02-15 11:35:00+00",
        "updated_at": "2026-02-15 11:35:00+00",
        "tribes": "[]",
        "rarity": "super raro"
    },
    {
        "id": "c4d5e6f7-g8h9-4i0j-1k2l-m3n4o5p6q7r8",
        "name": "Lago Ilusionário",
        "image_file_id": null,
        "image_url": null,
        "initiative_elements": "[\"water\"]",
        "abilities": "[{\"effectType\": \"lose_element\", \"targetScope\": \"engaged_creatures\", \"targetTribes\": [], \"stats\": [\"none\"], \"value\": 0, \"cardTypes\": [\"creature\"], \"battleRules\": {\"type\": \"generic_special\", \"requiresTarget\": true, \"usageLimitPerTurn\": null, \"notes\": \"Remove o elemento Água de criaturas engajadas.\", \"payload\": {\"element\": \"water\", \"cannotGainBack\": true}}, \"description\": \"Criaturas engajadas perdem o tipo Elemental Água e não podem ganhá-lo\"}, {\"effectType\": \"lose_element\", \"targetScope\": \"all_creatures\", \"targetTribes\": [], \"stats\": [\"none\"], \"value\": 0, \"cardTypes\": [\"creature\"], \"battleRules\": {\"type\": \"generic_special\", \"requiresTarget\": true, \"usageLimitPerTurn\": null, \"notes\": \"Miragem: remove o elemento Água de criaturas neste espaço.\", \"payload\": {\"element\": \"water\", \"cannotGainBack\": true, \"mirage\": true}}, \"description\": \"Miragem: Criaturas perdem o tipo Elemental Água e não podem ganhá-lo\"}]",
        "created_at": "2026-02-15 11:35:00+00",
        "updated_at": "2026-02-15 11:35:00+00",
        "tribes": "[]",
        "rarity": "super raro"
    },
    {
        "id": "d5e6f7g8-h9i0-4j1k-2l3m-n4o5p6q7r8s9",
        "name": "Muralhas Imaginárias",
        "image_file_id": null,
        "image_url": null,
        "initiative_elements": "[\"danian\"]",
        "abilities": "[{\"effectType\": \"special\", \"targetScope\": \"none\", \"targetTribes\": [], \"stats\": [\"none\"], \"value\": 0, \"cardTypes\": [\"mugic\"], \"battleRules\": {\"type\": \"generic_special\", \"requiresTarget\": false, \"usageLimitPerTurn\": 1, \"notes\": \"Oponente pode retornar 1 carta de Mugic da pilha de descarte para a mão.\", \"payload\": {\"trigger\": \"on_location_activate\", \"targetPlayer\": \"opponent\", \"action\": \"return_mugic_from_discard\", \"amount\": 1}}, \"description\": \"Quando este se torna o Local ativo, seu oponente pode retornar uma carta de Mugic da pilha de descarte para a mão dele\"}, {\"effectType\": \"decrease\", \"targetScope\": \"specific_tribes\", \"targetTribes\": [\"marrillian\"], \"stats\": [\"none\"], \"value\": 10, \"cardTypes\": [\"attack\"], \"battleRules\": {\"type\": \"stat_modifier\", \"requiresTarget\": true, \"usageLimitPerTurn\": null, \"notes\": \"Aplica também em criaturas Minion.\", \"payload\": {\"includesMinion\": true, \"appliesTo\": \"attack_damage_received\"}}, \"description\": \"Ataques causam 10 a menos de dano a Criaturas M'arrillian e Minion\"}, {\"effectType\": \"special\", \"targetScope\": \"none\", \"targetTribes\": [], \"stats\": [\"none\"], \"value\": 0, \"cardTypes\": [\"location\"], \"battleRules\": {\"type\": \"generic_special\", \"requiresTarget\": false, \"usageLimitPerTurn\": null, \"notes\": \"Único\", \"payload\": {\"unique\": true}}, \"description\": \"Único\"}]",
        "created_at": "2026-02-15 11:35:00+00",
        "updated_at": "2026-02-15 11:35:00+00",
        "tribes": "[\"danian\"]",
        "rarity": "comum"
    },
    {
        "id": "e3f4g5h6-i7j8-4k9l-0m1n-o2p3q4r5s6t7",
        "name": "Pilar de Jade",
        "image_file_id": null,
        "image_url": null,
        "initiative_elements": "[\"power\"]",
        "abilities": "[{\"effectType\": \"special\", \"targetScope\": \"none\", \"targetTribes\": [], \"stats\": [\"none\"], \"value\": 0, \"cardTypes\": [\"location\"], \"battleRules\": {\"type\": \"jade_pillar_counter_damage\", \"requiresTarget\": false, \"usageLimitPerTurn\": null, \"notes\": \"Gerencia marcadores de Jade e causa 50 de dano ao final.\", \"payload\": {\"initialCounters\": 10, \"damagePerCounterSpent\": 5, \"finalDamage\": 50}}, \"description\": \"Quando o Pilar de Jade se torna o Local ativo, coloque 10 marcadores de Jade sobre ele. Remova um marcador de Jade do Pilar de Jade para cada 5 de dano de ataque causado. Quando o último marcador for removido, o Pilar de Jade causa 50 de dano à Criatura que jogou o último ataque\"}]",
        "created_at": "2026-02-15 11:40:00+00",
        "updated_at": "2026-02-15 11:40:00+00",
        "tribes": "[]",
        "rarity": "ultra raro"
    },
    {
        "id": "f4g5h6i7-j8k9-4l0m-1n2o-p3q4r5s6t7u8",
        "name": "Lagoa de Lava",
        "image_file_id": null,
        "image_url": null,
        "initiative_elements": "[\"power\"]",
        "abilities": "[{\"effectType\": \"special\", \"targetScope\": \"none\", \"targetTribes\": [], \"stats\": [\"none\"], \"value\": 0, \"cardTypes\": [\"mugic\"], \"battleRules\": {\"type\": \"mugic_name_lock_this_turn\", \"requiresTarget\": false, \"usageLimitPerTurn\": 1, \"notes\": \"Revela Mugic aleatória e bloqueia nomes iguais neste turno.\", \"payload\": {\"trigger\": \"on_location_activate\"}}, \"description\": \"Quando este se torna o Local ativo, cada jogador revela uma carta de Mugic aleatória de sua mão. Cartas com o mesmo nome das cartas reveladas não podem ser jogadas neste turno\"}, {\"effectType\": \"decrease\", \"targetScope\": \"specific_tribes\", \"targetTribes\": [\"marrillian\"], \"stats\": [\"none\"], \"value\": 5, \"cardTypes\": [\"creature\"], \"battleRules\": {\"type\": \"stat_modifier\", \"requiresTarget\": true, \"usageLimitPerTurn\": null, \"notes\": \"Aplica também em criaturas Minion.\", \"payload\": {\"includesMinion\": true, \"appliesTo\": \"mugic_and_ability_damage_received\"}}, \"description\": \"Criaturas M'arrillian e Minion recebem 5 a menos de dano de Mugic e habilidades\"}]",
        "created_at": "2026-02-15 11:40:00+00",
        "updated_at": "2026-02-15 11:40:00+00",
        "tribes": "[]",
        "rarity": "comum"
    },
    {
        "id": "g5h6i7j8-k9l0-4m1n-2o3p-q4r5s6t7u8v9",
        "name": "Torre de Catapulta de Mommark",
        "image_file_id": null,
        "image_url": null,
        "initiative_elements": "[\"speed\"]",
        "abilities": "[{\"effectType\": \"gain\", \"targetScope\": \"own_creatures\", \"targetTribes\": [], \"stats\": [\"none\"], \"value\": 1, \"cardTypes\": [\"creature\"], \"battleRules\": {\"type\": \"generic_special\", \"requiresTarget\": true, \"usageLimitPerTurn\": 1, \"notes\": \"Concede Ligeiro 1 para suas criaturas quando o local ativa.\", \"payload\": {\"trigger\": \"on_location_activate\", \"keyword\": \"swift\", \"amount\": 1}}, \"description\": \"Quando este se torna o Local ativo, Criaturas que você controla ganham Ligeiro 1\"}]",
        "created_at": "2026-02-15 11:40:00+00",
        "updated_at": "2026-02-15 11:40:00+00",
        "tribes": "[]",
        "rarity": "comum"
    },
    {
        "id": "h6i7j8k9-l0m1-4n2o-3p4q-r5s6t7u8v9w0",
        "name": "Reservatório do Pilar do Monte",
        "image_file_id": null,
        "image_url": null,
        "initiative_elements": "[\"courage\"]",
        "abilities": "[{\"effectType\": \"special\", \"targetScope\": \"none\", \"targetTribes\": [], \"stats\": [\"none\"], \"value\": 0, \"cardTypes\": [\"creature\"], \"battleRules\": {\"type\": \"return_chieftain_from_discard\", \"requiresTarget\": false, \"usageLimitPerTurn\": 1, \"notes\": \"Cada jogador pode retornar um Chieftain da pilha de descarte.\", \"payload\": {\"trigger\": \"on_location_activate\", \"requiresEmptySpace\": true}}, \"description\": \"Quando este se torna o Local ativo, cada jogador pode retornar um Chieftain de sua pilha de descarte para jogar em um espaço desocupado em seu lado do Tabuleiro sem contadores de Mugic\"}, {\"effectType\": \"gain\", \"targetScope\": \"specific_tribes\", \"targetTribes\": [\"marrillian\"], \"stats\": [\"none\"], \"value\": 5, \"cardTypes\": [\"creature\"], \"battleRules\": {\"type\": \"stat_modifier\", \"requiresTarget\": true, \"usageLimitPerTurn\": null, \"notes\": \"Aplica também em criaturas Minion.\", \"payload\": {\"includesMinion\": true, \"keyword\": \"water\", \"amount\": 5}}, \"description\": \"Criaturas M'arrillian e Minion ganham Água 5\"}]",
        "created_at": "2026-02-15 11:40:00+00",
        "updated_at": "2026-02-15 11:40:00+00",
        "tribes": "[]",
        "rarity": "comum"
    },
    {
        "id": "e5b6c7d8-f9a0-4b1c-2d3e-4f5g6h7i8j9k",
        "name": "Porta das Minas Profundas",
        "image_file_id": null,
        "image_url": null,
        "initiative_elements": "[\"speed\"]",
        "abilities": "[{\"effectType\": \"gain\", \"targetScope\": \"all_creatures\", \"targetTribes\": [], \"stats\": [\"energy\"], \"value\": 10, \"cardTypes\": [\"creature\"], \"battleRules\": {\"type\": \"stat_modifier\", \"requiresTarget\": true, \"usageLimitPerTurn\": null, \"notes\": \"Aplica apenas em criaturas com ataques de Água.\", \"payload\": {\"condition\": \"has_attack_element\", \"element\": \"water\"}}, \"description\": \"Criaturas com Ataques de Água ganham 10 de Energia\"}]",
        "created_at": "2026-02-15 12:10:00+00",
        "updated_at": "2026-02-15 12:10:00+00",
        "tribes": "[]",
        "rarity": "super raro"
    },
    {
        "id": "f6a7b8c9-d0e1-4f2g-3h4i-5j6k7l8m9n0o",
        "name": "Biblioteca do Outro Mundo",
        "image_file_id": null,
        "image_url": null,
        "initiative_elements": "[\"water\"]",
        "abilities": "[{\"effectType\": \"increase\", \"targetScope\": \"engaged_creatures\", \"targetTribes\": [], \"stats\": [\"wisdom\"], \"value\": 5, \"cardTypes\": [\"creature\"], \"battleRules\": {\"type\": \"stat_modifier\", \"requiresTarget\": true, \"usageLimitPerTurn\": null, \"notes\": \"Criaturas engajadas ganham Superar Sabedoria 5.\", \"payload\": {\"keyword\": \"outperform\"}}, \"description\": \"Criaturas engajadas ganham Superar Sabedoria 5\"}, {\"effectType\": \"decrease\", \"targetScope\": \"all_creatures\", \"targetTribes\": [], \"stats\": [\"courage\"], \"value\": 5, \"cardTypes\": [\"attack\"], \"battleRules\": {\"type\": \"stat_modifier\", \"requiresTarget\": false, \"usageLimitPerTurn\": null, \"notes\": \"Reduz em 5 dano de ataques de Coragem.\", \"payload\": {\"appliesTo\": \"attack_damage\", \"attackStat\": \"courage\"}}, \"description\": \"O dano causado por Ataques de Coragem é reduzido em 5\"}]",
        "created_at": "2026-02-15 12:10:00+00",
        "updated_at": "2026-02-15 12:10:00+00",
        "tribes": "[]",
        "rarity": "incomum"
    },
    {
        "id": "a1b2c3d4-e5f6-4g7h-8i9j-0k1l2m3n4o5p",
        "name": "Os Fossos",
        "image_file_id": null,
        "image_url": null,
        "initiative_elements": "[\"power\"]",
        "abilities": "[{\"effectType\": \"increase\", \"targetScope\": \"all_creatures\", \"targetTribes\": [], \"stats\": [\"power\"], \"value\": 10, \"cardTypes\": [\"creature\"], \"battleRules\": {\"type\": \"stat_modifier\", \"requiresTarget\": true, \"usageLimitPerTurn\": null, \"notes\": \"Aplica apenas em criaturas com ataques de Fogo.\", \"payload\": {\"condition\": \"has_attack_element\", \"element\": \"fire\"}}, \"description\": \"Criaturas com Ataques de Fogo ganham 10 de Poder\"}]",
        "created_at": "2026-02-15 12:10:00+00",
        "updated_at": "2026-02-15 12:10:00+00",
        "tribes": "[]",
        "rarity": "incomum"
    },
    {
        "id": "b2c3d4e5-f6g7-4h8i-9j0k-1l2m3n4o5p6q",
        "name": "Câmara de Loucura de Psykdoom",
        "image_file_id": null,
        "image_url": null,
        "initiative_elements": "[\"wisdom\"]",
        "abilities": "[{\"effectType\": \"special\", \"targetScope\": \"none\", \"targetTribes\": [], \"stats\": [\"none\"], \"value\": 0, \"cardTypes\": [\"attack\"], \"battleRules\": {\"type\": \"discard_attack_cards_from_deck\", \"requiresTarget\": false, \"usageLimitPerTurn\": 1, \"notes\": \"Cada jogador descarta 2 cartas de seu baralho de ataques.\", \"payload\": {\"amount\": 2}}, \"description\": \"Quando esta se torna o Local ativo, cada jogador descarta 2 cartas de seu Baralho de Ataques\"}]",
        "created_at": "2026-02-15 12:10:00+00",
        "updated_at": "2026-02-15 12:10:00+00",
        "tribes": "[]",
        "rarity": "comum"
    },
    {
        "id": "c3d4e5f6-g7h8-4i9j-0k1l-2m3n4o5p6q7r",
        "name": "Rao'Pa Sahkk, Base de Operações de Ihun'kalin",
        "initiative_elements": "[\"speed\"]",
        "rarity": "rara",
        "abilities": "[{\"effectType\": \"special\", \"targetScope\": \"none\", \"targetTribes\": [], \"stats\": [\"none\"], \"value\": 0, \"cardTypes\": [\"equipment\"], \"battleRules\": {\"type\": \"generic_special\", \"requiresTarget\": false, \"usageLimitPerTurn\": 1, \"notes\": \"Cada jogador sacrifica um Battlegear quando o local se torna ativo.\", \"payload\": {\"trigger\": \"on_location_activate\", \"action\": \"sacrifice_battlegear\"}}, \"description\": \"Quando este se torna o Local ativo, cada jogador sacrifica um Battlegear.\"}, {\"effectType\": \"increase\", \"targetScope\": \"specific_tribes\", \"targetTribes\": [\"marrillian\"], \"stats\": [\"energy\"], \"value\": 5, \"cardTypes\": [\"creature\"], \"battleRules\": {\"type\": \"stat_modifier\", \"requiresTarget\": true, \"usageLimitPerTurn\": null, \"notes\": \"Aplica também em criaturas Minion.\", \"payload\": {\"includesMinion\": true, \"trigger\": \"on_win_challenge\"}}, \"description\": \"Quando uma Criatura M'arrillian ou Minion vence um Desafio, essa Criatura ganha 5 de Energia.\"}]"
    },
    {
        "id": "d4e5f6g7-h8i9-4j0k-1l2m-3n4o5p6q7r8s",
        "name": "Terras do Rio, Base de Operações de Erak'tabb",
        "initiative_elements": "[\"wisdom\"]",
        "rarity": "rara",
        "abilities": "[{\"effectType\": \"special\", \"targetScope\": \"none\", \"targetTribes\": [], \"stats\": [\"none\"], \"value\": 0, \"cardTypes\": [\"creature\"], \"battleRules\": {\"type\": \"generic_special\", \"requiresTarget\": true, \"usageLimitPerTurn\": 1, \"notes\": \"Cada jogador remove um contador de Mugic de uma criatura que controla.\", \"payload\": {\"trigger\": \"on_location_activate\", \"action\": \"remove_mugic_counter\", \"amount\": 1}}, \"description\": \"Quando este se torna o Local ativo, cada jogador remove um contador de Mugic de uma Criatura que controla.\"}, {\"effectType\": \"decrease\", \"targetScope\": \"specific_tribes\", \"targetTribes\": [\"marrillian\"], \"stats\": [\"none\"], \"value\": 5, \"cardTypes\": [\"attack\"], \"battleRules\": {\"type\": \"stat_modifier\", \"requiresTarget\": true, \"usageLimitPerTurn\": null, \"notes\": \"Aplica também em criaturas Minion.\", \"payload\": {\"includesMinion\": true, \"appliesTo\": \"attack_damage_received\"}}, \"description\": \"Criaturas M'arrillian e Minion recebem 5 a menos de dano de Cartas de Ataque.\"}]"
    },
    {
        "id": "e5f6g7h8-i9j0-4k1l-2m3n-4o5p6q7r8s9t",
        "name": "Campos de Tempestade (Stormgrounds)",
        "initiative_elements": "[\"courage\"]",
        "rarity": "incomum",
        "abilities": "[{\"effectType\": \"special\", \"targetScope\": \"none\", \"targetTribes\": [\"marrillian\"], \"stats\": [\"none\"], \"value\": 0, \"cardTypes\": [\"creature\"], \"battleRules\": {\"type\": \"minion_activated_ability_cost_increase\", \"requiresTarget\": false, \"usageLimitPerTurn\": null, \"notes\": \"Habilidades ativadas de Minion custam 1 Mugic adicional.\", \"payload\": {\"costIncrease\": 1, \"includesMinion\": true}}, \"description\": \"Habilidades ativadas de Criaturas Minion custam um contador de Mugic adicional para serem jogadas.\"}]"
    },
    {
        "id": "f6g7h8i9-j0k1-4l2m-3n4o-5p6q7r8s9t0u",
        "name": "Caverna de Projeção de Ulmar",
        "initiative_elements": "[\"water\"]",
        "rarity": "super rara",
        "abilities": "[{\"effectType\": \"special\", \"targetScope\": \"none\", \"targetTribes\": [], \"stats\": [\"none\"], \"value\": 0, \"cardTypes\": [\"location\"], \"battleRules\": {\"type\": \"reveal_new_active_location\", \"requiresTarget\": false, \"usageLimitPerTurn\": 1, \"notes\": \"Quando o local ativa, o oponente revela um novo local ativo.\", \"payload\": {\"trigger\": \"on_location_activate\", \"targetPlayer\": \"opponent\"}}, \"description\": \"Quando a Caverna de Projeção de Ulmar se torna o Local ativo, seu oponente revela um novo Local ativo.\"}, {\"effectType\": \"special\", \"targetScope\": \"own_creatures\", \"targetTribes\": [], \"stats\": [\"none\"], \"value\": 0, \"cardTypes\": [\"creature\"], \"battleRules\": {\"type\": \"relocate_to_empty_space_on_action_step\", \"requiresTarget\": true, \"usageLimitPerTurn\": null, \"notes\": \"Miragem de realocação no início da etapa de ação.\", \"payload\": {\"trigger\": \"on_action_step_start\", \"requiresEmptySpace\": true}}, \"description\": \"Miragem: No início da Etapa de Ação de cada jogador, se este espaço estiver desocupado, aquele jogador pode realocar uma de suas Criaturas para este espaço.\"}]"
    },
    {
        "id": "g7h8i9j0-k1l2-4m3n-5o6p-7q8r9s0t1u2v",
        "name": "Banquete de Van Bloot",
        "initiative_elements": "[\"underworld\"]",
        "rarity": "super rara",
        "abilities": "[{\"effectType\": \"increase\", \"targetScope\": \"specific_tribes\", \"targetTribes\": [\"marrillian\"], \"stats\": [\"energy\"], \"value\": 5, \"cardTypes\": [\"creature\"], \"battleRules\": {\"type\": \"stat_modifier\", \"requiresTarget\": true, \"usageLimitPerTurn\": null, \"notes\": \"Aplica também em criaturas Minion.\", \"payload\": {\"includesMinion\": true}}, \"description\": \"Criaturas M'arrillian e Minion ganham 5 de Energia.\"}, {\"effectType\": \"increase\", \"targetScope\": \"own_creatures\", \"targetTribes\": [], \"stats\": [\"all\"], \"value\": 20, \"cardTypes\": [\"creature\"], \"battleRules\": {\"type\": \"generic_special\", \"requiresTarget\": true, \"usageLimitPerTurn\": null, \"notes\": \"Aplica quando sua criatura engajada perde a iniciativa.\", \"payload\": {\"trigger\": \"on_lose_initiative\", \"condition\": \"engaged\"}}, \"description\": \"Quando sua Criatura engajada perde a Iniciativa, ela ganha 20 em todas as Disciplinas.\"}]"
    },
    {
        "id": "h8i9j0k1-l2m3-4n5o-6p7q-8r9s0t1u2v3w",
        "name": "Refeitório de Vidav",
        "initiative_elements": "[\"wisdom\"]",
        "rarity": "incomum",
        "abilities": "[{\"effectType\": \"special\", \"targetScope\": \"none\", \"targetTribes\": [], \"stats\": [\"none\"], \"value\": 0, \"cardTypes\": [\"attack\"], \"battleRules\": {\"type\": \"draw_then_discard_attack_cards\", \"requiresTarget\": false, \"usageLimitPerTurn\": 1, \"notes\": \"Cada jogador compra 2 cartas de ataque e depois descarta 2.\", \"payload\": {\"draw\": 2, \"discard\": 2}}, \"description\": \"Quando este se torna o Local ativo, cada jogador compra duas Cartas de Ataque, depois descarta duas Cartas de Ataque.\"}]"
    }
]